registro4.v
module registro4 (
    input wire [3:0] dato_in,  
    input wire ejecutar,       
    output reg [3:0] q         
);

    always @(posedge ejecutar) begin
        q <= dato_in;
    end

endmodule

shifter/shifter_left.v
module shifter_left (
    input wire [3:0] A,
    input wire [1:0] B,
    output wire [3:0] C
);

    wire x1, x2, x3, x4, x5, x6, x7, x8, x9, x10, x11, x12, x13, x14, x15, x16, x17, x18, x19, x20, x21, x22, x23, x24, x25, x26, x27, x28, x29, x30, x31, x32;

//Primer dígito
    nor g1 (x1, B[0], B[1]);
    and g2 (C[0], A[0], x1);

//Segundo dígito
    and g3 (x3, A[0], B[0]);
    not g4 (x4, B[0]);
    and g5 (x5, A[1], x4);
    xor g6 (x6, x3, x5);
    not g7 (x7, B[1]);
    and g8 (C[1], x7, x6);

//Tercer dígito
    not g9 (x8, B[0]);
    and g90 (x9, x8, B[1]);
    and g10 (x10, x9, A[0]);
    not g11 (x11, B[1]);
    and g12 (x12, B[0], x11);
    and g13 (x13, A[1], x12);
    nor g14 (x14, B[0], B[1]);
    and g15 (x15, A[2], x14);
    or g16 (x16, x15, x13);
    or g17 (C[2], x16, x10);

//Cuarto dígito
    nor g21 (x21, B[0], B[1]);
    and g22 (x22, A[3], x21);
    not g23 (x23, B[1]);
    and g24 (x24, B[0], x23);
    and g25 (x25, x24, A[2]);
    or g26 (x26, x22, x25);
    not g27 (x27, B[0]);
    and g28 (x28, x27, B[1]);
    and g29 (x29, x28, A[1]);
    and g30 (x30, B[0], B[1]);
    and g31 (x31, x30, A[0]);
    or g32 (x32, x31, x29);
    or g33 (C[3], x26, x32);



endmodule

shifter/shifter_right.v
module shifter_right (
    input wire [3:0] A,
    input wire [1:0] B,
    output wire [3:0] C
);

    wire [3:0] A_invertido;
    wire [3:0] C_intermedio;

    assign A_invertido = {A[0], A[1], A[2], A[3]};

    shifter_left g_shift_l (
        .A(A_invertido),
        .B(B),
        .C(C_intermedio)
    );


    assign C = {C_intermedio[0], C_intermedio[1], C_intermedio[2], C_intermedio[3]};

endmodule

full_adder.v
module full_adder (
    input wire Bit1,
    input wire Bit2,
    input wire CarryIn,
    output wire Salida,
    output wire CarryOut
);

    wire x1, x2, x3;

    xor g1 (x1, Bit1, Bit2);
    and g2 (x2, Bit1, Bit2);
    xor g3 (Salida, CarryIn, x1);
    and g4 (x3, CarryIn, x1);
    or g5 (CarryOut, x2, x3);

endmodule

fpga_build/half_adder.v
module half_adder (
    input wire Bit1,
    input wire Bit2,
    output wire Salida,
    output wire Carry
);

    xor g1 (Salida, Bit1, Bit2);
    and g2 (Carry, Bit1, Bit2);

endmodule

bit4_adder.v
module bit4_adder (
    input wire [3:0] A,
    input wire [3:0] B,
    output wire [3:0] Salida
);

    wire carry1, carry2, carry3, carry4, salida1, salida2, salida3, salida4;

    
    half_adder g1 (.Bit1(A[0]), .Bit2(B[0]), .Salida(salida1), .Carry(carry1));
   
    full_adder g2 (.Bit1(A[1]), .Bit2(B[1]), .CarryIn(carry1), .Salida(salida2), .CarryOut(carry2));
   
    full_adder g3 (.Bit1(A[2]), .Bit2(B[2]), .CarryIn(carry2), .Salida(salida3), .CarryOut(carry3));
    
     full_adder g4 (.Bit1(A[3]), .Bit2(B[3]), .CarryIn(carry3), .Salida(salida4), .CarryOut(carry4));
    assign Salida = {salida4, salida3, salida2, salida1};

endmodule

bit4_sub.v
module bit4_sub (
    input wire [3:0] A,
    input wire [3:0] B,
    output wire [3:0] Salida
);

    wire [3:0] B_comp1;

    not g0 (B_comp1[0], B[0]);
    not g1 (B_comp1[1], B[1]);
    not g2 (B_comp1[2], B[2]);
    not g3 (B_comp1[3], B[3]);

    wire [3:0] salida1;

    bit4_adder g4 (.A(A), .B(B_comp1), Salida(salida1));

    wire [3:0] binario1;

    assign binario1 = 4'b0001;

    bit4_adder g5 (.A(salida1), .B(binario1), .Salida(Salida));

endmodule

bit4_inv_sub.v
module bit4_inv_sub (
    input wire [3:0] A,
    input wire [3:0] B,
    output wire [3:0] Salida
);

    bit4_sub g1 (Salida, B, A);

endmodule

fpga_build/calculadora.v
module calculadora (
    input wire [3:0] op1,          // Primer operando
    input wire [3:0] op2,          // Segundo operando externo
    input wire selector_op2,      // 0: usar op2, 1: usar resultado anterior (R)
    input wire [2:0] opcode,       // Código de operación (3 bits)
    input wire ejecutar,          // Señal para ejecutar/capturar el resultado
    output wire [3:0] resultado    // Resultado final (salida del registro)
);

    // --- Señales internas ---
    wire [3:0] op2_seleccionado;  // Segundo operando (op2 o R)
    wire [3:0] resultado_combinacional; // Resultado de la operación seleccionada

    // --- MUX para seleccionar el segundo operando ---
    // Si selector_op2 = 1, usa el resultado anterior (R); si no, usa op2.
    // Implementación del MUX con compuertas (sin usar ? :)
    wire [3:0] R; // Salida del registro (retroalimentación)
    assign op2_seleccionado = (selector_op2) ? R : op2;
    // NOTA: Si no puedes usar el operador ternario, reemplázalo con:
    // assign op2_seleccionado = {4{selector_op2}} & R | {~4{selector_op2}} & op2;

    // --- Instanciar los módulos de operaciones ---
    // Suma
    wire [3:0] suma_result;
    bit4_adder suma (
        .A(op1),
        .B(op2_seleccionado),
        .Salida(suma_result)
    );

    // Resta (A - B)
    wire [3:0] resta_result;
    bit4_sub resta (
        .A(op1),
        .B(op2_seleccionado),
        .Salida(resta_result)
    );

    // Resta inversa (B - A)
    wire [3:0] resta_inv_result;
    bit4_inv_sub resta_inv (
        .A(op1),
        .B(op2_seleccionado),
        .Salida(resta_inv_result)
    );

    // Shift left
    wire [3:0] shift_left_result;
    shifter_left shift_left (
        .A(op1),
        .B(op2_seleccionado[1:0]), // Usamos B[1:0] para el shift (0 a 3)
        .C(shift_left_result)
    );

    // Shift right
    wire [3:0] shift_right_result;
    shifter_right shift_right (
        .A(op1),
        .B(op2_seleccionado[1:0]),
        .C(shift_right_result)
    );

    // --- MUX para seleccionar la operación según el opcode ---
    // Implementación con compuertas (sin usar case o if)
    // Decodificar el opcode:
    wire opcode_000 = ~opcode[2] & ~opcode[1] & ~opcode[0]; // Reinicio
    wire opcode_001 = ~opcode[2] & ~opcode[1] & opcode[0];   // Suma
    wire opcode_010 = ~opcode[2] & opcode[1] & ~opcode[0];  // Resta
    wire opcode_011 = ~opcode[2] & opcode[1] & opcode[0];   // Resta inversa
    wire opcode_100 = opcode[2] & ~opcode[1] & ~opcode[0];   // Shift left
    wire opcode_101 = opcode[2] & ~opcode[1] & opcode[0];    // Shift right

    // Asignar el resultado combinacional según el opcode
    // Usamos AND/OR para seleccionar la operación activa
    assign resultado_combinacional =
        (opcode_000) ? 4'b0000 : // Reinicio
        (opcode_001) ? suma_result :
        (opcode_010) ? resta_result :
        (opcode_011) ? resta_inv_result :
        (opcode_100) ? shift_left_result :
        (opcode_101) ? shift_right_result :
        4'b0000; // Default (por seguridad)

    // NOTA: Si no puedes usar el operador ternario, implementa un MUX con compuertas:
    // Ejemplo para 2 operaciones (extiende para 6):
    // wire [3:0] mux_out = (opcode_001 & suma_result) | (opcode_010 & resta_result) | ...;

    // --- Registro para guardar el resultado ---
    registro4 reg_result (
        .dato_in(resultado_combinacional),
        .ejecutar(ejecutar),
        .q(R)
    );

    // --- Salida del módulo ---
    assign resultado = R;

endmodule

tb_calculadora.v
`timescale 1ns/1ps

module tb_calculadora;

    // --- Declaración de señales para el módulo bajo prueba (DUT) ---
    reg [3:0] op1;
    reg [3:0] op2;
    reg selector_op2;
    reg [2:0] opcode;
    reg ejecutar;

    wire [3:0] resultado;

    // --- Instanciar el módulo principal ---
    // NOTA: Asegúrate de que el nombre del módulo coincida con tu archivo (ej: calculadora_top o calculadora)
    calculadora dut (
        .op1(op1),
        .op2(op2),
        .selector_op2(selector_op2),
        .opcode(opcode),
        .ejecutar(ejecutar),
        .resultado(resultado)
    );

    // --- Generar archivo .vcd para GTKWave ---
    initial begin
        $dumpfile("tb_calculadora.vcd");
        $dumpvars(0, dut);
    end

    // --- Testbench: Aplicar casos de prueba ---
    initial begin
        // Inicializar todas las entradas
        op1 = 4'b0000;
        op2 = 4'b0000;
        selector_op2 = 0;
        opcode = 3'b000;
        ejecutar = 0;

        // Esperar 10 ns para estabilizar la simulación
        #10;

        // --- Caso 1: Reinicio (opcode = 000) ---
        opcode = 3'b000;
        op1 = 4'b1010; // Ejemplo: 10 en decimal
        op2 = 4'b1101; // Ejemplo: -3 en complemento a dos
        selector_op2 = 0;
        #10;
        ejecutar = 1; // Pulso de ejecución
        #10;
        ejecutar = 0;
        #10;
        $display("Caso 1 - Reinicio: op1=%b, op2=%b, opcode=%b, resultado=%b (esperado: 0000)",
                 op1, op2, opcode, resultado);

        // --- Caso 2: Suma (opcode = 001) ---
        opcode = 3'b001;
        op1 = 4'b0011; // 3
        op2 = 4'b0100; // 4
        selector_op2 = 0;
        #10;
        ejecutar = 1;
        #10;
        ejecutar = 0;
        #10;
        $display("Caso 2 - Suma: op1=%b (%d), op2=%b (%d), resultado=%b (%d, esperado: 0111 = 7)",
                 op1, $signed(op1), op2, $signed(op2), resultado, $signed(resultado));

        // --- Caso 3: Resta (opcode = 010) ---
        opcode = 3'b010;
        op1 = 4'b0101; // 5
        op2 = 4'b0011; // 3
        selector_op2 = 0;
        #10;
        ejecutar = 1;
        #10;
        ejecutar = 0;
        #10;
        $display("Caso 3 - Resta: op1=%b (%d), op2=%b (%d), resultado=%b (%d, esperado: 0010 = 2)",
                 op1, $signed(op1), op2, $signed(op2), resultado, $signed(resultado));

        // --- Caso 4: Resta inversa (opcode = 011) ---
        opcode = 3'b011;
        op1 = 4'b0010; // 2
        op2 = 4'b0100; // 4
        selector_op2 = 0;
        #10;
        ejecutar = 1;
        #10;
        ejecutar = 0;
        #10;
        $display("Caso 4 - Resta inversa: op1=%b (%d), op2=%b (%d), resultado=%b (%d, esperado: 0010 = 2)",
                 op1, $signed(op1), op2, $signed(op2), resultado, $signed(resultado));

        // --- Caso 5: Shift left (opcode = 100) ---
        opcode = 3'b100;
        op1 = 4'b0001; // 1
        op2 = 4'b0010; // 2 (B[1:0] = 10, shift de 2 posiciones)
        selector_op2 = 0;
        #10;
        ejecutar = 1;
        #10;
        ejecutar = 0;
        #10;
        $display("Caso 5 - Shift left: op1=%b (%d), op2=%b (shift=%d), resultado=%b (%d, esperado: 0100 = 4)",
                 op1, $signed(op1), op2, op2[1:0], resultado, $signed(resultado));

        // --- Caso 6: Shift right (opcode = 101) ---
        opcode = 3'b101;
        op1 = 4'b1000; // -8 en complemento a dos
        op2 = 4'b0001; // 1 (B[1:0] = 01, shift de 1 posición)
        selector_op2 = 0;
        #10;
        ejecutar = 1;
        #10;
        ejecutar = 0;
        #10;
        $display("Caso 6 - Shift right: op1=%b (%d), op2=%b (shift=%d), resultado=%b (%d, esperado: 1100 = -4)",
                 op1, $signed(op1), op2, op2[1:0], resultado, $signed(resultado));

        // --- Caso 7: Usar resultado anterior como segundo operando (selector_op2 = 1) ---
        opcode = 3'b001; // Suma
        op1 = 4'b0011; // 3
        op2 = 4'b0100; // 4
        selector_op2 = 0;
        #10;
        ejecutar = 1;
        #10;
        ejecutar = 0;
        #10;
        $display("Caso 7a - Suma inicial: op1=%b, op2=%b, resultado=%b", op1, op2, resultado);

        // Ahora usa el resultado anterior (R) como segundo operando
        selector_op2 = 1; // Usar R como op2
        op1 = 4'b0010; // 2
        opcode = 3'b001; // Suma de nuevo
        #10;
        ejecutar = 1;
        #10;
        ejecutar = 0;
        #10;
        $display("Caso 7b - Suma con R: op1=%b, op2=R=%b, resultado=%b (esperado: 0111 + 0010 = 1001 = 9)",
                 op1, resultado, resultado);

        // --- Caso 8: Número negativo en complemento a dos ---
        opcode = 3'b010; // Resta
        op1 = 4'b0010; // 2
        op2 = 4'b1101; // -3 en complemento a dos
        selector_op2 = 0;
        #10;
        ejecutar = 1;
        #10;
        ejecutar = 0;
        #10;
        $display("Caso 8 - Resta con negativo: op1=%b (%d), op2=%b (%d), resultado=%b (%d, esperado: 0111 = 5)",
                 op1, $signed(op1), op2, $signed(op2), resultado, $signed(resultado));

        // --- Finalizar simulación ---
        #100;
        $display("Simulación terminada.");
        $finish;
    end

endmodule

tb_calculadora.vcd
$date
	Mon Sep  7 14:33:21 2026
$end
$version
	Icarus Verilog
$end
$timescale
	1ps
$end
$scope module tb_calculadora $end
$scope module dut $end
$var wire 1 ! ejecutar $end
$var wire 4 " op1 [3:0] $end
$var wire 4 # op2 [3:0] $end
$var wire 3 $ opcode [2:0] $end
$var wire 1 % opcode_000 $end
$var wire 1 & opcode_001 $end
$var wire 1 ' opcode_010 $end
$var wire 1 ( opcode_011 $end
$var wire 1 ) opcode_100 $end
$var wire 1 * opcode_101 $end
$var wire 4 + resultado [3:0] $end
$var wire 1 , selector_op2 $end
$var wire 4 - suma_result [3:0] $end
$var wire 4 . shift_right_result [3:0] $end
$var wire 4 / shift_left_result [3:0] $end
$var wire 4 0 resultado_combinacional [3:0] $end
$var wire 4 1 resta_result [3:0] $end
$var wire 4 2 resta_inv_result [3:0] $end
$var wire 4 3 op2_seleccionado [3:0] $end
$var wire 4 4 R [3:0] $end
$scope module reg_result $end
$var wire 4 5 dato_in [3:0] $end
$var wire 1 ! ejecutar $end
$var reg 4 6 q [3:0] $end
$upscope $end
$scope module resta $end
$var wire 4 7 A [3:0] $end
$var wire 4 8 B [3:0] $end
$var wire 4 9 binario1 [3:0] $end
$var wire 4 : salida1 [3:0] $end
$var wire 4 ; Salida [3:0] $end
$var wire 4 < B_comp1 [3:0] $end
$scope module g4 $end
$var wire 4 = A [3:0] $end
$var wire 4 > B [3:0] $end
$var wire 1 ? salida4 $end
$var wire 1 @ salida3 $end
$var wire 1 A salida2 $end
$var wire 1 B salida1 $end
$var wire 1 C carry4 $end
$var wire 1 D carry3 $end
$var wire 1 E carry2 $end
$var wire 1 F carry1 $end
$var wire 4 G Salida [3:0] $end
$scope module g1 $end
$var wire 1 H Bit1 $end
$var wire 1 I Bit2 $end
$var wire 1 F Carry $end
$var wire 1 B Salida $end
$upscope $end
$scope module g2 $end
$var wire 1 J Bit1 $end
$var wire 1 K Bit2 $end
$var wire 1 F CarryIn $end
$var wire 1 E CarryOut $end
$var wire 1 A Salida $end
$var wire 1 L x1 $end
$var wire 1 M x2 $end
$var wire 1 N x3 $end
$upscope $end
$scope module g3 $end
$var wire 1 O Bit1 $end
$var wire 1 P Bit2 $end
$var wire 1 E CarryIn $end
$var wire 1 D CarryOut $end
$var wire 1 @ Salida $end
$var wire 1 Q x1 $end
$var wire 1 R x2 $end
$var wire 1 S x3 $end
$upscope $end
$scope module g4 $end
$var wire 1 T Bit1 $end
$var wire 1 U Bit2 $end
$var wire 1 D CarryIn $end
$var wire 1 C CarryOut $end
$var wire 1 ? Salida $end
$var wire 1 V x1 $end
$var wire 1 W x2 $end
$var wire 1 X x3 $end
$upscope $end
$upscope $end
$scope module g5 $end
$var wire 4 Y A [3:0] $end
$var wire 4 Z B [3:0] $end
$var wire 1 [ salida4 $end
$var wire 1 \ salida3 $end
$var wire 1 ] salida2 $end
$var wire 1 ^ salida1 $end
$var wire 1 _ carry4 $end
$var wire 1 ` carry3 $end
$var wire 1 a carry2 $end
$var wire 1 b carry1 $end
$var wire 4 c Salida [3:0] $end
$scope module g1 $end
$var wire 1 d Bit1 $end
$var wire 1 e Bit2 $end
$var wire 1 b Carry $end
$var wire 1 ^ Salida $end
$upscope $end
$scope module g2 $end
$var wire 1 f Bit1 $end
$var wire 1 g Bit2 $end
$var wire 1 b CarryIn $end
$var wire 1 a CarryOut $end
$var wire 1 ] Salida $end
$var wire 1 h x1 $end
$var wire 1 i x2 $end
$var wire 1 j x3 $end
$upscope $end
$scope module g3 $end
$var wire 1 k Bit1 $end
$var wire 1 l Bit2 $end
$var wire 1 a CarryIn $end
$var wire 1 ` CarryOut $end
$var wire 1 \ Salida $end
$var wire 1 m x1 $end
$var wire 1 n x2 $end
$var wire 1 o x3 $end
$upscope $end
$scope module g4 $end
$var wire 1 p Bit1 $end
$var wire 1 q Bit2 $end
$var wire 1 ` CarryIn $end
$var wire 1 _ CarryOut $end
$var wire 1 [ Salida $end
$var wire 1 r x1 $end
$var wire 1 s x2 $end
$var wire 1 t x3 $end
$upscope $end
$upscope $end
$upscope $end
$scope module resta_inv $end
$var wire 4 u A [3:0] $end
$var wire 4 v B [3:0] $end
$var wire 4 w Salida [3:0] $end
$scope module g1 $end
$var wire 4 x A [3:0] $end
$var wire 4 y B [3:0] $end
$var wire 4 z binario1 [3:0] $end
$var wire 4 { salida1 [3:0] $end
$var wire 4 | Salida [3:0] $end
$var wire 4 } B_comp1 [3:0] $end
$scope module g4 $end
$var wire 4 ~ A [3:0] $end
$var wire 4 !" B [3:0] $end
$var wire 1 "" salida4 $end
$var wire 1 #" salida3 $end
$var wire 1 $" salida2 $end
$var wire 1 %" salida1 $end
$var wire 1 &" carry4 $end
$var wire 1 '" carry3 $end
$var wire 1 (" carry2 $end
$var wire 1 )" carry1 $end
$var wire 4 *" Salida [3:0] $end
$scope module g1 $end
$var wire 1 +" Bit1 $end
$var wire 1 ," Bit2 $end
$var wire 1 )" Carry $end
$var wire 1 %" Salida $end
$upscope $end
$scope module g2 $end
$var wire 1 -" Bit1 $end
$var wire 1 ." Bit2 $end
$var wire 1 )" CarryIn $end
$var wire 1 (" CarryOut $end
$var wire 1 $" Salida $end
$var wire 1 /" x1 $end
$var wire 1 0" x2 $end
$var wire 1 1" x3 $end
$upscope $end
$scope module g3 $end
$var wire 1 2" Bit1 $end
$var wire 1 3" Bit2 $end
$var wire 1 (" CarryIn $end
$var wire 1 '" CarryOut $end
$var wire 1 #" Salida $end
$var wire 1 4" x1 $end
$var wire 1 5" x2 $end
$var wire 1 6" x3 $end
$upscope $end
$scope module g4 $end
$var wire 1 7" Bit1 $end
$var wire 1 8" Bit2 $end
$var wire 1 '" CarryIn $end
$var wire 1 &" CarryOut $end
$var wire 1 "" Salida $end
$var wire 1 9" x1 $end
$var wire 1 :" x2 $end
$var wire 1 ;" x3 $end
$upscope $end
$upscope $end
$scope module g5 $end
$var wire 4 <" A [3:0] $end
$var wire 4 =" B [3:0] $end
$var wire 1 >" salida4 $end
$var wire 1 ?" salida3 $end
$var wire 1 @" salida2 $end
$var wire 1 A" salida1 $end
$var wire 1 B" carry4 $end
$var wire 1 C" carry3 $end
$var wire 1 D" carry2 $end
$var wire 1 E" carry1 $end
$var wire 4 F" Salida [3:0] $end
$scope module g1 $end
$var wire 1 G" Bit1 $end
$var wire 1 H" Bit2 $end
$var wire 1 E" Carry $end
$var wire 1 A" Salida $end
$upscope $end
$scope module g2 $end
$var wire 1 I" Bit1 $end
$var wire 1 J" Bit2 $end
$var wire 1 E" CarryIn $end
$var wire 1 D" CarryOut $end
$var wire 1 @" Salida $end
$var wire 1 K" x1 $end
$var wire 1 L" x2 $end
$var wire 1 M" x3 $end
$upscope $end
$scope module g3 $end
$var wire 1 N" Bit1 $end
$var wire 1 O" Bit2 $end
$var wire 1 D" CarryIn $end
$var wire 1 C" CarryOut $end
$var wire 1 ?" Salida $end
$var wire 1 P" x1 $end
$var wire 1 Q" x2 $end
$var wire 1 R" x3 $end
$upscope $end
$scope module g4 $end
$var wire 1 S" Bit1 $end
$var wire 1 T" Bit2 $end
$var wire 1 C" CarryIn $end
$var wire 1 B" CarryOut $end
$var wire 1 >" Salida $end
$var wire 1 U" x1 $end
$var wire 1 V" x2 $end
$var wire 1 W" x3 $end
$upscope $end
$upscope $end
$upscope $end
$upscope $end
$scope module shift_left $end
$var wire 4 X" A [3:0] $end
$var wire 2 Y" B [1:0] $end
$var wire 1 Z" x1 $end
$var wire 1 [" x10 $end
$var wire 1 \" x11 $end
$var wire 1 ]" x12 $end
$var wire 1 ^" x13 $end
$var wire 1 _" x14 $end
$var wire 1 `" x15 $end
$var wire 1 a" x16 $end
$var wire 1 b" x21 $end
$var wire 1 c" x22 $end
$var wire 1 d" x23 $end
$var wire 1 e" x24 $end
$var wire 1 f" x25 $end
$var wire 1 g" x26 $end
$var wire 1 h" x27 $end
$var wire 1 i" x28 $end
$var wire 1 j" x29 $end
$var wire 1 k" x3 $end
$var wire 1 l" x30 $end
$var wire 1 m" x31 $end
$var wire 1 n" x32 $end
$var wire 1 o" x4 $end
$var wire 1 p" x5 $end
$var wire 1 q" x6 $end
$var wire 1 r" x7 $end
$var wire 1 s" x8 $end
$var wire 1 t" x9 $end
$var wire 4 u" C [3:0] $end
$upscope $end
$scope module shift_right $end
$var wire 4 v" A [3:0] $end
$var wire 2 w" B [1:0] $end
$var wire 4 x" C_intermedio [3:0] $end
$var wire 4 y" C [3:0] $end
$var wire 4 z" A_invertido [3:0] $end
$scope module g_shift_l $end
$var wire 4 {" A [3:0] $end
$var wire 2 |" B [1:0] $end
$var wire 1 }" x1 $end
$var wire 1 ~" x10 $end
$var wire 1 !# x11 $end
$var wire 1 "# x12 $end
$var wire 1 ## x13 $end
$var wire 1 $# x14 $end
$var wire 1 %# x15 $end
$var wire 1 &# x16 $end
$var wire 1 '# x21 $end
$var wire 1 (# x22 $end
$var wire 1 )# x23 $end
$var wire 1 *# x24 $end
$var wire 1 +# x25 $end
$var wire 1 ,# x26 $end
$var wire 1 -# x27 $end
$var wire 1 .# x28 $end
$var wire 1 /# x29 $end
$var wire 1 0# x3 $end
$var wire 1 1# x30 $end
$var wire 1 2# x31 $end
$var wire 1 3# x32 $end
$var wire 1 4# x4 $end
$var wire 1 5# x5 $end
$var wire 1 6# x6 $end
$var wire 1 7# x7 $end
$var wire 1 8# x8 $end
$var wire 1 9# x9 $end
$var wire 4 :# C [3:0] $end
$upscope $end
$upscope $end
$scope module suma $end
$var wire 4 ;# A [3:0] $end
$var wire 4 <# B [3:0] $end
$var wire 1 =# salida4 $end
$var wire 1 ># salida3 $end
$var wire 1 ?# salida2 $end
$var wire 1 @# salida1 $end
$var wire 1 A# carry4 $end
$var wire 1 B# carry3 $end
$var wire 1 C# carry2 $end
$var wire 1 D# carry1 $end
$var wire 4 E# Salida [3:0] $end
$scope module g1 $end
$var wire 1 F# Bit1 $end
$var wire 1 G# Bit2 $end
$var wire 1 D# Carry $end
$var wire 1 @# Salida $end
$upscope $end
$scope module g2 $end
$var wire 1 H# Bit1 $end
$var wire 1 I# Bit2 $end
$var wire 1 D# CarryIn $end
$var wire 1 C# CarryOut $end
$var wire 1 ?# Salida $end
$var wire 1 J# x1 $end
$var wire 1 K# x2 $end
$var wire 1 L# x3 $end
$upscope $end
$scope module g3 $end
$var wire 1 M# Bit1 $end
$var wire 1 N# Bit2 $end
$var wire 1 C# CarryIn $end
$var wire 1 B# CarryOut $end
$var wire 1 ># Salida $end
$var wire 1 O# x1 $end
$var wire 1 P# x2 $end
$var wire 1 Q# x3 $end
$upscope $end
$scope module g4 $end
$var wire 1 R# Bit1 $end
$var wire 1 S# Bit2 $end
$var wire 1 B# CarryIn $end
$var wire 1 A# CarryOut $end
$var wire 1 =# Salida $end
$var wire 1 T# x1 $end
$var wire 1 U# x2 $end
$var wire 1 V# x3 $end
$upscope $end
$upscope $end
$upscope $end
$upscope $end
$enddefinitions $end
$comment Show the parameter values. $end
$dumpall
$end
#0
$dumpvars
0V#
0U#
0T#
0S#
0R#
0Q#
0P#
0O#
0N#
0M#
0L#
0K#
0J#
0I#
0H#
0G#
0F#
b0 E#
0D#
0C#
0B#
0A#
0@#
0?#
0>#
0=#
b0 <#
b0 ;#
b0 :#
09#
18#
17#
06#
05#
14#
03#
02#
01#
00#
0/#
0.#
1-#
0,#
0+#
0*#
1)#
0(#
1'#
0&#
0%#
1$#
0##
0"#
1!#
0~"
1}"
b0 |"
b0 {"
b0 z"
b0 y"
b0 x"
b0 w"
b0 v"
b0 u"
0t"
1s"
1r"
0q"
0p"
1o"
0n"
0m"
0l"
0k"
0j"
0i"
1h"
0g"
0f"
0e"
1d"
0c"
1b"
0a"
0`"
1_"
0^"
0]"
1\"
0["
1Z"
b0 Y"
b0 X"
1W"
0V"
1U"
0T"
1S"
1R"
0Q"
1P"
0O"
1N"
1M"
0L"
1K"
0J"
1I"
1H"
1G"
b0 F"
1E"
1D"
1C"
1B"
0A"
0@"
0?"
0>"
b1 ="
b1111 <"
0;"
0:"
19"
18"
07"
06"
05"
14"
13"
02"
01"
00"
1/"
1."
0-"
1,"
0+"
b1111 *"
0)"
0("
0'"
0&"
1%"
1$"
1#"
1""
b1111 !"
b0 ~
b1111 }
b0 |
b1111 {
b1 z
b0 y
b0 x
b0 w
b0 v
b0 u
1t
0s
1r
0q
1p
1o
0n
1m
0l
1k
1j
0i
1h
0g
1f
1e
1d
b0 c
1b
1a
1`
1_
0^
0]
0\
0[
b1 Z
b1111 Y
0X
0W
1V
1U
0T
0S
0R
1Q
1P
0O
0N
0M
1L
1K
0J
1I
0H
b1111 G
0F
0E
0D
0C
1B
1A
1@
1?
b1111 >
b0 =
b1111 <
b0 ;
b1111 :
b1 9
b0 8
b0 7
bx 6
b0 5
bx 4
b0 3
b0 2
b0 1
b0 0
b0 /
b0 .
b0 -
0,
bx +
0*
0)
0(
0'
0&
1%
b0 $
b0 #
b0 "
0!
$end
#10000
0B"
0C"
0>"
0W"
0`
1^
0b
0D"
0?"
0R"
0U"
0a
1\
0o
0_
1a"
1,#
0d
1@"
0M"
0P"
0S"
1&"
0]
0j
1m
0X
b1101 1
b1101 ;
b1101 c
1[
0t
1^"
16#
1+#
0B
0Q
b11 2
b11 w
b11 |
b11 F"
1A"
0E"
0N"
0""
1;"
0h
1k
0D
1r
0Z"
0o"
0s"
1]"
0_"
0b"
1e"
0h"
0}"
10#
04#
08#
1"#
0$#
0'#
1*#
0-#
0I
0P
0U
0G"
0#"
1'"
1>#
1A#
0f
1@
0S
1p
0/"
b100 /
b100 u"
0&#
b101 .
b101 y"
b10 <
b10 >
b10 {
b10 *"
b10 <"
0%"
1)"
04"
15"
1@#
1O#
1U#
0A
1E
b1100 :
b1100 G
b1100 Y
1?
0C
0."
08"
0q"
0g"
0%#
b1010 x"
b1010 :#
1?#
b111 -
b111 E#
0=#
b1 Y"
b1 w"
b1 |"
1+"
12"
17"
1G#
1N#
1S#
0L
1M
1V
0W
b101 }
b101 !"
0p"
0c"
1J#
0T#
b1101 3
b1101 8
b1101 v
b1101 x
b1101 ~
b1101 <#
1J
1T
b101 z"
b101 {"
1H#
1R#
b1101 #
b1010 "
b1010 7
b1010 =
b1010 u
b1010 y
b1010 X"
b1010 v"
b1010 ;#
#20000
b0 +
b0 4
b0 6
1!
#30000
0!
#40000
1h
1f
b1 2
b1 w
b1 |
b1 F"
0@"
0a"
1&#
1A
0K"
1[
b11 .
b11 y"
0B#
1p"
0^"
1%#
1(#
0+#
1F
0I"
1]
1r
b1100 x"
b1100 :#
1>#
0Q#
1Z"
1o"
1s"
0]"
1_"
1b"
0e"
1h"
1}"
14#
18#
0"#
1$#
1'#
0*#
1-#
1I
1U
b0 {
b0 *"
b0 <"
0$"
b1111 1
b1111 ;
b1111 c
1^
0b
1p
b11 /
b11 u"
06#
0C#
b111 0
b111 5
b1011 <
b1011 >
0)"
0d
1?
0,"
18"
1q"
00#
1?#
0L#
0=#
0A#
0%
b0 Y"
b0 w"
b0 |"
0+"
07"
0G#
0S#
b1110 :
b1110 G
b1110 Y
0B
1V
b1100 }
b1100 !"
0k"
b111 -
b111 E#
1@#
0D#
0T#
0U#
1&
b100 3
b100 8
b100 v
b100 x
b100 ~
b100 <#
1H
0T
b1100 z"
b1100 {"
1F#
0R#
b100 #
b11 "
b11 7
b11 =
b11 u
b11 y
b11 X"
b11 v"
b11 ;#
b1 $
#50000
b111 +
b111 4
b111 6
1!
#60000
0!
#70000
1?"
1>"
0[
0^
1b
1P"
1U"
0r
0g"
1n"
0,#
03#
1d
1@"
1N"
1S"
0&"
1Q#
1]
b10 1
b10 ;
b10 c
0\
0p
1C
b0 .
b0 y"
0["
0f"
1m"
0##
0(#
0/#
1B
0F
1R
b1110 2
b1110 w
b1110 |
b1110 F"
0A"
1E"
1#"
1""
0;"
1C#
0h
0m
0?
1X
b0 x"
b0 :#
0Z"
1k"
0o"
0r"
0s"
0t"
0\"
0]"
0_"
0b"
0d"
0e"
0h"
0i"
1l"
0}"
04#
07#
08#
09#
0!#
0"#
0$#
0'#
0)#
0*#
0-#
0.#
11#
0I
0K
1P
1G"
1("
0'"
1L#
0f
0k
1D
b1000 /
b1000 u"
0&#
06#
1=#
b10 0
b10 5
b1100 <
b1100 >
b1101 {
b1101 *"
b1101 <"
1%"
10"
05"
0@#
1D#
0A
0N
0E
b1 :
b1 G
b1 Y
0@
0S
1."
03"
1q"
0a"
0%#
05#
0?#
b1000 -
b1000 E#
0>#
1B#
0%
1'
b11 Y"
b11 w"
b11 |"
1+"
1-"
02"
1G#
1I#
0N#
0L
0M
0Q
b1010 }
b1010 !"
0p"
0`"
1J#
1O#
0P#
0&
b11 3
b11 8
b11 v
b11 x
b11 ~
b11 <#
0J
1O
b1010 z"
b1010 {"
0H#
1M#
b11 #
b101 "
b101 7
b101 =
b101 u
b101 y
b101 X"
b101 v"
b101 ;#
b10 $
#80000
b10 +
b10 4
b10 6
1!
#90000
0!
