full_adder.v
module full_adder (
    input wire Bit1,
    input wire Bit2,
    input wire CarryIn,
    output wire Salida,
    output wire CarryOut
);

    wire x1, x2, x3;

    xor g1 (x1, Bit1, Bit2);
    and g2 (x2, Bit1, Bit2);
    xor g3 (Salida, CarryIn, x1);
    and g4 (x3, CarryIn, x1);
    or g5 (CarryOut, x2, x3);

endmodule

tb_full_adder.v
`timescale 1ns/1ps

module tb_full_adder;
    reg Bit1, Bit2, CarryIn;
    wire Salida, CarryOut;

    full_adder uut (
        .Bit1(Bit1),
        .Bit2(Bit2),
        .CarryIn(CarryIn),
        .Salida(Salida),
        .CarryOut(CarryOut)
    );

    initial begin
        $dumpfile("tb_full_adder.vcd");
        $dumpvars(0, tb_full_adder);
        $monitor("t=%0t Bit1=%b Bit2=%b CarryIn=%b | Salida=%b CarryOut=%b",
                  $time, Bit1, Bit2, CarryIn, Salida, CarryOut);

        // 000
        Bit1 = 0; Bit2 = 0; CarryIn = 0; #10;
        // 001
        Bit1 = 0; Bit2 = 0; CarryIn = 1; #10;
        // 010
        Bit1 = 0; Bit2 = 1; CarryIn = 0; #10;
        // 011
        Bit1 = 0; Bit2 = 1; CarryIn = 1; #10;
        // 100
        Bit1 = 1; Bit2 = 0; CarryIn = 0; #10;
        // 101
        Bit1 = 1; Bit2 = 0; CarryIn = 1; #10;
        // 110
        Bit1 = 1; Bit2 = 1; CarryIn = 0; #10;
        // 111
        Bit1 = 1; Bit2 = 1; CarryIn = 1; #10;

        $finish;
    end
endmodule

tb_full_adder.vcd
$date
	Sun Sep 06 19:19:20 2026
$end
$version
	Icarus Verilog
$end
$timescale
	1ps
$end
$scope module tb_full_adder $end
$var wire 1 ! Salida $end
$var wire 1 " CarryOut $end
$var reg 1 # Bit1 $end
$var reg 1 $ Bit2 $end
$var reg 1 % CarryIn $end
$scope module uut $end
$var wire 1 # Bit1 $end
$var wire 1 $ Bit2 $end
$var wire 1 % CarryIn $end
$var wire 1 " CarryOut $end
$var wire 1 ! Salida $end
$var wire 1 & x1 $end
$var wire 1 ' x2 $end
$var wire 1 ( x3 $end
$upscope $end
$upscope $end
$enddefinitions $end
$comment Show the parameter values. $end
$dumpall
$end
#0
$dumpvars
0(
0'
0&
0%
0$
0#
0"
0!
$end
#10000
1!
1%
#20000
1&
0%
1$
#30000
1"
0!
1(
1%
#40000
0"
1!
0(
0%
0$
1#
#50000
1"
0!
1(
1%
#60000
0(
0&
1'
0%
1$
#70000
1!
1%
